LICENSE
MANIFEST.in
README.md
setup.py
spotted_on_spotify/__init__.py
spotted_on_spotify/__main__.py
spotted_on_spotify/app.py
spotted_on_spotify/conf.py
spotted_on_spotify/spotted_on_spotify.py
spotted_on_spotify/util.py
spotted_on_spotify.egg-info/PKG-INFO
spotted_on_spotify.egg-info/SOURCES.txt
spotted_on_spotify.egg-info/dependency_links.txt
spotted_on_spotify.egg-info/entry_points.txt
spotted_on_spotify.egg-info/requires.txt
spotted_on_spotify.egg-info/top_level.txt