Metadata-Version: 1.1
Name: spotted-on-spotify
Version: 1.0.0
Summary: Youtube/SoundCloud to Spotify python command line application.
Home-page: https://github.com/anthonymirand/SpottedOnSpotify-cmdline
Author: Anthony Mirand
Author-email: anthonypmirand@gmail.com
License: MIT
Keywords: spotify youtube soundcloud audio fingerprint
Platform: UNKNOWN
Classifier: Development Status :: 4 - Beta
Classifier: Intended Audience :: Developers
Classifier: Topic :: Multimedia :: Sound/Audio :: Analysis
Classifier: License :: OSI Approved :: MIT License
Classifier: Programming Language :: Python
Classifier: Programming Language :: Python :: 2.7
